datarobot_genai/__init__.py
datarobot_genai/py.typed
datarobot_genai/core/__init__.py
datarobot_genai/core/custom_model.py
datarobot_genai/core/telemetry_agent.py
datarobot_genai/core/agents/__init__.py
datarobot_genai/core/agents/base.py
datarobot_genai/core/chat/__init__.py
datarobot_genai/core/chat/auth.py
datarobot_genai/core/chat/client.py
datarobot_genai/core/chat/responses.py
datarobot_genai/core/cli/__init__.py
datarobot_genai/core/cli/agent_environment.py
datarobot_genai/core/cli/agent_kernel.py
datarobot_genai/core/mcp/__init__.py
datarobot_genai/core/mcp/common.py
datarobot_genai/core/utils/__init__.py
datarobot_genai/core/utils/auth.py
datarobot_genai/core/utils/urls.py
datarobot_genai/crewai/__init__.py
datarobot_genai/crewai/agent.py
datarobot_genai/crewai/events.py
datarobot_genai/crewai/mcp.py
datarobot_genai/drmcp/__init__.py
datarobot_genai/drmcp/server.py
datarobot_genai/drmcp/core/__init__.py
datarobot_genai/drmcp/core/auth.py
datarobot_genai/drmcp/core/clients.py
datarobot_genai/drmcp/core/config.py
datarobot_genai/drmcp/core/config_utils.py
datarobot_genai/drmcp/core/constants.py
datarobot_genai/drmcp/core/credentials.py
datarobot_genai/drmcp/core/dr_mcp_server.py
datarobot_genai/drmcp/core/dr_mcp_server_logo.py
datarobot_genai/drmcp/core/exceptions.py
datarobot_genai/drmcp/core/logging.py
datarobot_genai/drmcp/core/mcp_instance.py
datarobot_genai/drmcp/core/routes.py
datarobot_genai/drmcp/core/routes_utils.py
datarobot_genai/drmcp/core/server_life_cycle.py
datarobot_genai/drmcp/core/telemetry.py
datarobot_genai/drmcp/core/tool_config.py
datarobot_genai/drmcp/core/tool_filter.py
datarobot_genai/drmcp/core/utils.py
datarobot_genai/drmcp/core/dynamic_prompts/__init__.py
datarobot_genai/drmcp/core/dynamic_prompts/controllers.py
datarobot_genai/drmcp/core/dynamic_prompts/dr_lib.py
datarobot_genai/drmcp/core/dynamic_prompts/register.py
datarobot_genai/drmcp/core/dynamic_prompts/utils.py
datarobot_genai/drmcp/core/dynamic_tools/__init__.py
datarobot_genai-0.3.0.dist-info/METADATA
datarobot_genai-0.3.0.dist-info/WHEEL
datarobot_genai-0.3.0.dist-info/entry_points.txt
datarobot_genai-0.3.0.dist-info/licenses/AUTHORS
datarobot_genai-0.3.0.dist-info/licenses/LICENSE
datarobot_genai-0.3.0.dist-info/RECORD
